setup.py
sopts/__init__.py
sopts.egg-info/PKG-INFO
sopts.egg-info/SOURCES.txt
sopts.egg-info/dependency_links.txt
sopts.egg-info/not-zip-safe
sopts.egg-info/top_level.txt