Metadata-Version: 1.0
Name: sopts
Version: 0.1.0
Summary: command line argument parser
Home-page: UNKNOWN
Author: UNKNOWN
Author-email: UNKNOWN
License: GPLv3
Platform: UNKNOWN
